{"csw:GetRecordsResponse":{"xmlns:gml":"http://www.opengis.net/gml","xmlns:csw":"http://www.opengis.net/cat/csw/2.0.2","csw:SearchResults":{"expires":"2022-03-12T17:46:49Z","elementSet":"summary","iStoreRecord":[{"thumbnail":"\\pdf\\THUMBNAIL\\1957-TS0034.png","aw_rank":1000,"product_size":"142 KB","aw_library_id":"library2_lib","title":"Treaty Series 034/1957: Cmnd 136","uuid":"56d8e1ef-14e0-4150-9c19-8f5dbf42738b","lb_document_id":65769,"library":"library2_lib","document_path":"D:\\KVData\\Library2\\pdf\\1957-TS0034.pdf","level_code":0,"id":65769,"document_url":"https://treaties.fcdo.gov.uk/data/Library2\\pdf\\1957-TS0034.pdf","metaformat":"Other"},{"aw_search_query":"qs=[*],qt=[16],qr=[false],qf=[library==>library2_lib||]","thumbnail":"\\pdf\\THUMBNAIL\\1957-TS0035.png","aw_rank":1000,"product_size":"960 KB","aw_library_id":"library2_lib","title":"Treaty Series 035/1957: Cmnd 137","uuid":"97a27609-2142-4465-8007-dfd109067692","lb_document_id":65770,"library":"library2_lib","document_path":"D:\\KVData\\Library2\\pdf\\1957-TS0035.pdf","level_code":0,"id":65770,"document_url":"https://treaties.fcdo.gov.uk/data/Library2\\pdf\\1957-TS0035.pdf","metaformat":"Other"},{"aw_search_query":"qs=[*],qt=[16],qr=[false],qf=[library==>library2_lib||]","thumbnail":"\\pdf\\THUMBNAIL\\1957-TS0036.png","aw_rank":1000,"product_size":"259 KB","aw_library_id":"library2_lib","title":"Treaty Series 036/1957: Cmnd 148","uuid":"32c78ba5-9916-40ca-8bb5-169d9badc372","lb_document_id":65771,"library":"library2_lib","document_path":"D:\\KVData\\Library2\\pdf\\1957-TS0036.pdf","level_code":0,"id":65771,"document_url":"https://treaties.fcdo.gov.uk/data/Library2\\pdf\\1957-TS0036.pdf","metaformat":"Other"},{"aw_search_query":"qs=[*],qt=[16],qr=[false],qf=[library==>library2_lib||]","thumbnail":"\\pdf\\THUMBNAIL\\1957-TS0037.png","aw_rank":1000,"product_size":"71 KB","aw_library_id":"library2_lib","title":"Treaty Series 037/1957: Cmnd 143","uuid":"8908ae3f-b40b-47d9-93c2-5b99769e9602","lb_document_id":65772,"library":"library2_lib","document_path":"D:\\KVData\\Library2\\pdf\\1957-TS0037.pdf","level_code":0,"id":65772,"document_url":"https://treaties.fcdo.gov.uk/data/Library2\\pdf\\1957-TS0037.pdf","metaformat":"Other"},{"aw_search_query":"qs=[*],qt=[16],qr=[false],qf=[library==>library2_lib||]","thumbnail":"\\pdf\\THUMBNAIL\\1957-TS0038.png","aw_rank":1000,"product_size":"174 KB","aw_library_id":"library2_lib","title":"Treaty Series 038/1957: Cmnd 144","uuid":"2f5dc962-3366-4bb8-8455-5fba2d50e3f4","lb_document_id":65773,"library":"library2_lib","document_path":"D:\\KVData\\Library2\\pdf\\1957-TS0038.pdf","level_code":0,"id":65773,"document_url":"https://treaties.fcdo.gov.uk/data/Library2\\pdf\\1957-TS0038.pdf","metaformat":"Other"},{"aw_search_query":"qs=[*],qt=[16],qr=[false],qf=[library==>library2_lib||]","thumbnail":"\\pdf\\THUMBNAIL\\1957-TS0039.png","aw_rank":1000,"product_size":"529 KB","aw_library_id":"library2_lib","title":"Treaty Series 039/1957: Cmnd 186","uuid":"8c4ae737-b167-4ef2-8fa5-6c8498972ea7","lb_document_id":65774,"library":"library2_lib","document_path":"D:\\KVData\\Library2\\pdf\\1957-TS0039.pdf","level_code":0,"id":65774,"document_url":"https://treaties.fcdo.gov.uk/data/Library2\\pdf\\1957-TS0039.pdf","metaformat":"Other"},{"aw_search_query":"qs=[*],qt=[16],qr=[false],qf=[library==>library2_lib||]","thumbnail":"\\pdf\\THUMBNAIL\\1957-TS0040.png","aw_rank":1000,"product_size":"946 KB","aw_library_id":"library2_lib","title":"Treaty Series 040/1957: Cmnd 170","uuid":"b934825b-9d78-47ce-85a0-ca2c4c63530d","lb_document_id":65775,"library":"library2_lib","document_path":"D:\\KVData\\Library2\\pdf\\1957-TS0040.pdf","level_code":0,"id":65775,"document_url":"https://treaties.fcdo.gov.uk/data/Library2\\pdf\\1957-TS0040.pdf","metaformat":"Other"},{"aw_search_query":"qs=[*],qt=[16],qr=[false],qf=[library==>library2_lib||]","thumbnail":"\\pdf\\THUMBNAIL\\1957-TS0041.png","aw_rank":1000,"product_size":"68 KB","aw_library_id":"library2_lib","title":"Treaty Series 041/1957: Cmnd 171","uuid":"e0a8cb00-b59c-4c73-9f9c-3609f0738dd7","lb_document_id":65776,"library":"library2_lib","document_path":"D:\\KVData\\Library2\\pdf\\1957-TS0041.pdf","level_code":0,"id":65776,"document_url":"https://treaties.fcdo.gov.uk/data/Library2\\pdf\\1957-TS0041.pdf","metaformat":"Other"},{"aw_search_query":"qs=[*],qt=[16],qr=[false],qf=[library==>library2_lib||]","thumbnail":"\\pdf\\THUMBNAIL\\1957-TS0042.png","aw_rank":1000,"product_size":"865 KB","aw_library_id":"library2_lib","title":"Treaty Series 042/1957: Cmnd 173","uuid":"9620ddb3-429e-41b2-938c-56d85dcf8db0","lb_document_id":65777,"library":"library2_lib","document_path":"D:\\KVData\\Library2\\pdf\\1957-TS0042.pdf","level_code":0,"id":65777,"document_url":"https://treaties.fcdo.gov.uk/data/Library2\\pdf\\1957-TS0042.pdf","metaformat":"Other"},{"aw_search_query":"qs=[*],qt=[16],qr=[false],qf=[library==>library2_lib||]","thumbnail":"\\pdf\\THUMBNAIL\\1957-TS0043.png","aw_rank":1000,"product_size":"152 KB","aw_library_id":"library2_lib","title":"Treaty Series 043/1957: Cmnd 177","uuid":"77fc38ce-b54c-47e3-92a3-2c81664d7c36","lb_document_id":65778,"library":"library2_lib","document_path":"D:\\KVData\\Library2\\pdf\\1957-TS0043.pdf","level_code":0,"id":65778,"document_url":"https://treaties.fcdo.gov.uk/data/Library2\\pdf\\1957-TS0043.pdf","metaformat":"Other"},{"aw_search_query":"qs=[*],qt=[16],qr=[false],qf=[library==>library2_lib||]","thumbnail":"\\pdf\\THUMBNAIL\\1957-TS0044.png","aw_rank":1000,"product_size":"83 KB","aw_library_id":"library2_lib","title":"Treaty Series 044/1957: Cmnd 178","uuid":"8e629bd7-0cda-4866-8201-774c4bb2ea83","lb_document_id":65779,"library":"library2_lib","document_path":"D:\\KVData\\Library2\\pdf\\1957-TS0044.pdf","level_code":0,"id":65779,"document_url":"https://treaties.fcdo.gov.uk/data/Library2\\pdf\\1957-TS0044.pdf","metaformat":"Other"},{"aw_search_query":"qs=[*],qt=[16],qr=[false],qf=[library==>library2_lib||]","thumbnail":"\\pdf\\THUMBNAIL\\1957-TS0045.png","aw_rank":1000,"product_size":"80 KB","aw_library_id":"library2_lib","title":"Treaty Series 045/1957: Cmnd 187","uuid":"5032275e-df17-4f16-bf0f-a5fbf99f00c4","lb_document_id":65780,"library":"library2_lib","document_path":"D:\\KVData\\Library2\\pdf\\1957-TS0045.pdf","level_code":0,"id":65780,"document_url":"https://treaties.fcdo.gov.uk/data/Library2\\pdf\\1957-TS0045.pdf","metaformat":"Other"},{"aw_search_query":"qs=[*],qt=[16],qr=[false],qf=[library==>library2_lib||]","thumbnail":"\\pdf\\THUMBNAIL\\1957-TS0046.png","aw_rank":1000,"product_size":"1,443 KB","aw_library_id":"library2_lib","title":"Treaty Series 046/1957: Cmnd 192","uuid":"b594d06d-9b24-4288-9f8a-da0e45fba9d0","lb_document_id":65781,"library":"library2_lib","document_path":"D:\\KVData\\Library2\\pdf\\1957-TS0046.pdf","level_code":0,"id":65781,"document_url":"https://treaties.fcdo.gov.uk/data/Library2\\pdf\\1957-TS0046.pdf","metaformat":"Other"},{"aw_search_query":"qs=[*],qt=[16],qr=[false],qf=[library==>library2_lib||]","thumbnail":"\\pdf\\THUMBNAIL\\1957-TS0047.png","aw_rank":1000,"product_size":"195 KB","aw_library_id":"library2_lib","title":"Treaty Series 047/1957: Cmnd 198","uuid":"cf08842e-6e8a-4175-b8fd-1629ba211b58","lb_document_id":65782,"library":"library2_lib","document_path":"D:\\KVData\\Library2\\pdf\\1957-TS0047.pdf","level_code":0,"id":65782,"document_url":"https://treaties.fcdo.gov.uk/data/Library2\\pdf\\1957-TS0047.pdf","metaformat":"Other"},{"aw_search_query":"qs=[*],qt=[16],qr=[false],qf=[library==>library2_lib||]","thumbnail":"\\pdf\\THUMBNAIL\\1957-TS0048.png","aw_rank":1000,"product_size":"75 KB","aw_library_id":"library2_lib","title":"Treaty Series 048/1957: Cmnd 201","uuid":"935c06ba-f2d6-4af6-88f0-857e3f79ac03","lb_document_id":65783,"library":"library2_lib","document_path":"D:\\KVData\\Library2\\pdf\\1957-TS0048.pdf","level_code":0,"id":65783,"document_url":"https://treaties.fcdo.gov.uk/data/Library2\\pdf\\1957-TS0048.pdf","metaformat":"Other"},{"aw_search_query":"qs=[*],qt=[16],qr=[false],qf=[library==>library2_lib||]","thumbnail":"\\pdf\\THUMBNAIL\\1957-TS0049.png","aw_rank":1000,"product_size":"218 KB","aw_library_id":"library2_lib","title":"Treaty Series 049/1957: Cmnd 217","uuid":"2be2c7c9-62a4-426c-b800-0c0e061cfb68","lb_document_id":65784,"library":"library2_lib","document_path":"D:\\KVData\\Library2\\pdf\\1957-TS0049.pdf","level_code":0,"id":65784,"document_url":"https://treaties.fcdo.gov.uk/data/Library2\\pdf\\1957-TS0049.pdf","metaformat":"Other"},{"aw_search_query":"qs=[*],qt=[16],qr=[false],qf=[library==>library2_lib||]","thumbnail":"\\pdf\\THUMBNAIL\\1957-TS0050.png","aw_rank":1000,"product_size":"104 KB","aw_library_id":"library2_lib","title":"Treaty Series 050/1957: Cmnd 219","uuid":"8954466a-bd5a-4c3a-abcd-466eb9a13a59","lb_document_id":65785,"library":"library2_lib","document_path":"D:\\KVData\\Library2\\pdf\\1957-TS0050.pdf","level_code":0,"id":65785,"document_url":"https://treaties.fcdo.gov.uk/data/Library2\\pdf\\1957-TS0050.pdf","metaformat":"Other"},{"aw_search_query":"qs=[*],qt=[16],qr=[false],qf=[library==>library2_lib||]","thumbnail":"\\pdf\\THUMBNAIL\\1957-TS0051.png","aw_rank":1000,"product_size":"265 KB","aw_library_id":"library2_lib","title":"Treaty Series 051/1957: Cmnd 241","uuid":"865d7f2b-d439-4094-a3cd-23d02723e2f0","lb_document_id":65786,"library":"library2_lib","document_path":"D:\\KVData\\Library2\\pdf\\1957-TS0051.pdf","level_code":0,"id":65786,"document_url":"https://treaties.fcdo.gov.uk/data/Library2\\pdf\\1957-TS0051.pdf","metaformat":"Other"},{"aw_search_query":"qs=[*],qt=[16],qr=[false],qf=[library==>library2_lib||]","thumbnail":"\\pdf\\THUMBNAIL\\1957-TS0052.png","aw_rank":1000,"product_size":"320 KB","aw_library_id":"library2_lib","title":"Treaty Series 052/1957: Cmnd 236","uuid":"25a60f8c-5310-4a01-9b6e-75478b007e8d","lb_document_id":65787,"library":"library2_lib","document_path":"D:\\KVData\\Library2\\pdf\\1957-TS0052.pdf","level_code":0,"id":65787,"document_url":"https://treaties.fcdo.gov.uk/data/Library2\\pdf\\1957-TS0052.pdf","metaformat":"Other"},{"aw_search_query":"qs=[*],qt=[16],qr=[false],qf=[library==>library2_lib||]","thumbnail":"\\pdf\\THUMBNAIL\\1957-TS0053.png","aw_rank":1000,"product_size":"148 KB","aw_library_id":"library2_lib","title":"Treaty Series 053/1957: Cmnd 226","uuid":"826c0af9-7266-49ca-a531-83d77655ebfc","lb_document_id":65788,"library":"library2_lib","document_path":"D:\\KVData\\Library2\\pdf\\1957-TS0053.pdf","level_code":0,"id":65788,"document_url":"https://treaties.fcdo.gov.uk/data/Library2\\pdf\\1957-TS0053.pdf","metaformat":"Other"},{"aw_search_query":"qs=[*],qt=[16],qr=[false],qf=[library==>library2_lib||]","thumbnail":"\\pdf\\THUMBNAIL\\1957-TS0054.png","aw_rank":1000,"product_size":"106 KB","aw_library_id":"library2_lib","title":"Treaty Series 054/1957: Cmnd 238","uuid":"f094510d-5be1-40f0-a6f9-7c50df57f070","lb_document_id":65789,"library":"library2_lib","document_path":"D:\\KVData\\Library2\\pdf\\1957-TS0054.pdf","level_code":0,"id":65789,"document_url":"https://treaties.fcdo.gov.uk/data/Library2\\pdf\\1957-TS0054.pdf","metaformat":"Other"},{"aw_search_query":"qs=[*],qt=[16],qr=[false],qf=[library==>library2_lib||]","thumbnail":"\\pdf\\THUMBNAIL\\1957-TS0055.png","aw_rank":1000,"product_size":"388 KB","aw_library_id":"library2_lib","title":"Treaty Series 055/1957: Cmnd 244","uuid":"357a70e8-c4dd-433c-a691-242d991fbf13","lb_document_id":65790,"library":"library2_lib","document_path":"D:\\KVData\\Library2\\pdf\\1957-TS0055.pdf","level_code":0,"id":65790,"document_url":"https://treaties.fcdo.gov.uk/data/Library2\\pdf\\1957-TS0055.pdf","metaformat":"Other"},{"aw_search_query":"qs=[*],qt=[16],qr=[false],qf=[library==>library2_lib||]","thumbnail":"\\pdf\\THUMBNAIL\\1966-TS0028.png","aw_rank":1000,"product_size":"741 KB","aw_library_id":"library2_lib","title":"Treaty Series 028/1966: Cmnd 3001","uuid":"eae02d59-bf8f-4ae1-a539-1e82d24f902a","lb_document_id":66441,"library":"library2_lib","document_path":"D:\\KVData\\Library2\\pdf\\1966-TS0028.pdf","level_code":0,"id":66441,"document_url":"https://treaties.fcdo.gov.uk/data/Library2\\pdf\\1966-TS0028.pdf","metaformat":"Other"},{"aw_search_query":"qs=[*],qt=[16],qr=[false],qf=[library==>library2_lib||]","thumbnail":"\\pdf\\THUMBNAIL\\1966-TS0029.png","aw_rank":1000,"product_size":"141 KB","aw_library_id":"library2_lib","title":"Treaty Series 029/1966: Cmnd 2999","uuid":"0628d1b0-0a44-48c6-82da-36940444e6f3","lb_document_id":66442,"library":"library2_lib","document_path":"D:\\KVData\\Library2\\pdf\\1966-TS0029.pdf","level_code":0,"id":66442,"document_url":"https://treaties.fcdo.gov.uk/data/Library2\\pdf\\1966-TS0029.pdf","metaformat":"Other"},{"aw_search_query":"qs=[*],qt=[16],qr=[false],qf=[library==>library2_lib||]","thumbnail":"\\pdf\\THUMBNAIL\\1966-TS0030.png","aw_rank":1000,"product_size":"445 KB","aw_library_id":"library2_lib","title":"Treaty Series 030/1966: Cmnd 3002","uuid":"55206291-7828-427b-8c4b-128e4a5a34dc","lb_document_id":66443,"library":"library2_lib","document_path":"D:\\KVData\\Library2\\pdf\\1966-TS0030.pdf","level_code":0,"id":66443,"document_url":"https://treaties.fcdo.gov.uk/data/Library2\\pdf\\1966-TS0030.pdf","metaformat":"Other"},{"aw_search_query":"qs=[*],qt=[16],qr=[false],qf=[library==>library2_lib||]","thumbnail":"\\pdf\\THUMBNAIL\\1966-TS0031.png","aw_rank":1000,"product_size":"3,391 KB","aw_library_id":"library2_lib","title":"Treaty Series 031/1966: Cmnd 3026","uuid":"baa17ee2-a4aa-4045-b8d2-bcb40d0a1cf5","lb_document_id":66444,"library":"library2_lib","document_path":"D:\\KVData\\Library2\\pdf\\1966-TS0031.pdf","level_code":0,"id":66444,"document_url":"https://treaties.fcdo.gov.uk/data/Library2\\pdf\\1966-TS0031.pdf","metaformat":"Other"},{"aw_search_query":"qs=[*],qt=[16],qr=[false],qf=[library==>library2_lib||]","thumbnail":"\\pdf\\THUMBNAIL\\1966-TS0032.png","aw_rank":1000,"product_size":"1,151 KB","aw_library_id":"library2_lib","title":"Treaty Series 032/1966: Cmnd 3017","uuid":"450557d2-eb71-4950-8ab5-f68d6ae89cbf","lb_document_id":66445,"library":"library2_lib","document_path":"D:\\KVData\\Library2\\pdf\\1966-TS0032.pdf","level_code":0,"id":66445,"document_url":"https://treaties.fcdo.gov.uk/data/Library2\\pdf\\1966-TS0032.pdf","metaformat":"Other"},{"aw_search_query":"qs=[*],qt=[16],qr=[false],qf=[library==>library2_lib||]","thumbnail":"\\pdf\\THUMBNAIL\\1966-TS0033.png","aw_rank":1000,"product_size":"88 KB","aw_library_id":"library2_lib","title":"Treaty Series 033/1966: Cmnd 3009","uuid":"6f47cf71-7e68-4e1d-8d17-983909ef3319","lb_document_id":66446,"library":"library2_lib","document_path":"D:\\KVData\\Library2\\pdf\\1966-TS0033.pdf","level_code":0,"id":66446,"document_url":"https://treaties.fcdo.gov.uk/data/Library2\\pdf\\1966-TS0033.pdf","metaformat":"Other"},{"aw_search_query":"qs=[*],qt=[16],qr=[false],qf=[library==>library2_lib||]","thumbnail":"\\pdf\\THUMBNAIL\\1966-TS0034.png","aw_rank":1000,"product_size":"77 KB","aw_library_id":"library2_lib","title":"Treaty Series 034/1966: Cmnd 3010","uuid":"9d11068f-2086-4e26-89d1-25c33e20c166","lb_document_id":66447,"library":"library2_lib","document_path":"D:\\KVData\\Library2\\pdf\\1966-TS0034.pdf","level_code":0,"id":66447,"document_url":"https://treaties.fcdo.gov.uk/data/Library2\\pdf\\1966-TS0034.pdf","metaformat":"Other"},{"aw_search_query":"qs=[*],qt=[16],qr=[false],qf=[library==>library2_lib||]","thumbnail":"\\pdf\\THUMBNAIL\\1966-TS0035.png","aw_rank":1000,"product_size":"570 KB","aw_library_id":"library2_lib","title":"Treaty Series 035/1966: Cmnd 3011","uuid":"5eefa5a0-2481-4886-b1c4-e5b769069f18","lb_document_id":66448,"library":"library2_lib","document_path":"D:\\KVData\\Library2\\pdf\\1966-TS0035.pdf","level_code":0,"id":66448,"document_url":"https://treaties.fcdo.gov.uk/data/Library2\\pdf\\1966-TS0035.pdf","metaformat":"Other"},{"aw_search_query":"qs=[*],qt=[16],qr=[false],qf=[library==>library2_lib||]","thumbnail":"\\pdf\\THUMBNAIL\\1966-TS0038.png","aw_rank":1000,"product_size":"328 KB","aw_library_id":"library2_lib","title":"Treaty Series 038/1966: Cmnd 3013","uuid":"7cb50a8c-6c0e-4bca-b924-bc08821a84e1","lb_document_id":66449,"library":"library2_lib","document_path":"D:\\KVData\\Library2\\pdf\\1966-TS0038.pdf","level_code":0,"id":66449,"document_url":"https://treaties.fcdo.gov.uk/data/Library2\\pdf\\1966-TS0038.pdf","metaformat":"Other"},{"aw_search_query":"qs=[*],qt=[16],qr=[false],qf=[library==>library2_lib||]","thumbnail":"\\pdf\\THUMBNAIL\\1966-TS0039.png","aw_rank":1000,"product_size":"1,478 KB","aw_library_id":"library2_lib","title":"Treaty Series 039/1966: Cmnd 3028","uuid":"90083bc0-04b9-4d69-88e5-34d7f2651412","lb_document_id":66450,"library":"library2_lib","document_path":"D:\\KVData\\Library2\\pdf\\1966-TS0039.pdf","level_code":0,"id":66450,"document_url":"https://treaties.fcdo.gov.uk/data/Library2\\pdf\\1966-TS0039.pdf","metaformat":"Other"},{"aw_search_query":"qs=[*],qt=[16],qr=[false],qf=[library==>library2_lib||]","thumbnail":"\\pdf\\THUMBNAIL\\1966-TS0040.png","aw_rank":1000,"product_size":"122 KB","aw_library_id":"library2_lib","title":"Treaty Series 040/1966: Cmnd 3044","uuid":"96b0a227-935a-4d10-a660-b498d76a5e7a","lb_document_id":66451,"library":"library2_lib","document_path":"D:\\KVData\\Library2\\pdf\\1966-TS0040.pdf","level_code":0,"id":66451,"document_url":"https://treaties.fcdo.gov.uk/data/Library2\\pdf\\1966-TS0040.pdf","metaformat":"Other"},{"aw_search_query":"qs=[*],qt=[16],qr=[false],qf=[library==>library2_lib||]","thumbnail":"\\pdf\\THUMBNAIL\\1966-TS0041.png","aw_rank":1000,"product_size":"217 KB","aw_library_id":"library2_lib","title":"Treaty Series 041/1966: Cmnd 3048","uuid":"783706c7-337f-4b81-94d1-5255e27fe6d1","lb_document_id":66452,"library":"library2_lib","document_path":"D:\\KVData\\Library2\\pdf\\1966-TS0041.pdf","level_code":0,"id":66452,"document_url":"https://treaties.fcdo.gov.uk/data/Library2\\pdf\\1966-TS0041.pdf","metaformat":"Other"},{"aw_search_query":"qs=[*],qt=[16],qr=[false],qf=[library==>library2_lib||]","thumbnail":"\\pdf\\THUMBNAIL\\1966-TS0042.png","aw_rank":1000,"product_size":"205 KB","aw_library_id":"library2_lib","title":"Treaty Series 042/1966: Cmnd 3047","uuid":"46e113a5-79a9-41af-af0c-75a5d79301ba","lb_document_id":66453,"library":"library2_lib","document_path":"D:\\KVData\\Library2\\pdf\\1966-TS0042.pdf","level_code":0,"id":66453,"document_url":"https://treaties.fcdo.gov.uk/data/Library2\\pdf\\1966-TS0042.pdf","metaformat":"Other"},{"aw_search_query":"qs=[*],qt=[16],qr=[false],qf=[library==>library2_lib||]","thumbnail":"\\pdf\\THUMBNAIL\\1966-TS0043.png","aw_rank":1000,"product_size":"197 KB","aw_library_id":"library2_lib","title":"Treaty Series 043/1966: Cmnd 3049","uuid":"3877e7ed-1233-4980-ad93-7a7be6946b90","lb_document_id":66454,"library":"library2_lib","document_path":"D:\\KVData\\Library2\\pdf\\1966-TS0043.pdf","level_code":0,"id":66454,"document_url":"https://treaties.fcdo.gov.uk/data/Library2\\pdf\\1966-TS0043.pdf","metaformat":"Other"},{"aw_search_query":"qs=[*],qt=[16],qr=[false],qf=[library==>library2_lib||]","thumbnail":"\\pdf\\THUMBNAIL\\1966-TS0044.png","aw_rank":1000,"product_size":"121 KB","aw_library_id":"library2_lib","title":"Treaty Series 044/1966: Cmnd 3053","uuid":"d28fa253-8877-45ca-b182-05991297a1f8","lb_document_id":66455,"library":"library2_lib","document_path":"D:\\KVData\\Library2\\pdf\\1966-TS0044.pdf","level_code":0,"id":66455,"document_url":"https://treaties.fcdo.gov.uk/data/Library2\\pdf\\1966-TS0044.pdf","metaformat":"Other"},{"aw_search_query":"qs=[*],qt=[16],qr=[false],qf=[library==>library2_lib||]","thumbnail":"\\pdf\\THUMBNAIL\\1966-TS0048.png","aw_rank":1000,"product_size":"87 KB","aw_library_id":"library2_lib","title":"Treaty Series 048/1966: Cmnd 3077","uuid":"c7f53f86-a7e6-4aef-ba1e-2a6b88763068","lb_document_id":66456,"library":"library2_lib","document_path":"D:\\KVData\\Library2\\pdf\\1966-TS0048.pdf","level_code":0,"id":66456,"document_url":"https://treaties.fcdo.gov.uk/data/Library2\\pdf\\1966-TS0048.pdf","metaformat":"Other"},{"aw_search_query":"qs=[*],qt=[16],qr=[false],qf=[library==>library2_lib||]","thumbnail":"\\pdf\\THUMBNAIL\\1966-TS0049.png","aw_rank":1000,"product_size":"200 KB","aw_library_id":"library2_lib","title":"Treaty Series 049/1966: Cmnd 3078","uuid":"4ca56332-52bd-4bd9-b230-fe216b3a54c2","lb_document_id":66457,"library":"library2_lib","document_path":"D:\\KVData\\Library2\\pdf\\1966-TS0049.pdf","level_code":0,"id":66457,"document_url":"https://treaties.fcdo.gov.uk/data/Library2\\pdf\\1966-TS0049.pdf","metaformat":"Other"},{"aw_search_query":"qs=[*],qt=[16],qr=[false],qf=[library==>library2_lib||]","thumbnail":"\\pdf\\THUMBNAIL\\1966-TS0051.png","aw_rank":1000,"product_size":"100 KB","aw_library_id":"library2_lib","title":"Treaty Series 051/1966: Cmnd 3089","uuid":"56e1c3b8-df2f-4508-ba13-267493462ff3","lb_document_id":66458,"library":"library2_lib","document_path":"D:\\KVData\\Library2\\pdf\\1966-TS0051.pdf","level_code":0,"id":66458,"document_url":"https://treaties.fcdo.gov.uk/data/Library2\\pdf\\1966-TS0051.pdf","metaformat":"Other"},{"aw_search_query":"qs=[*],qt=[16],qr=[false],qf=[library==>library2_lib||]","thumbnail":"\\pdf\\THUMBNAIL\\1966-TS0052.png","aw_rank":1000,"product_size":"77 KB","aw_library_id":"library2_lib","title":"Treaty Series 052/1966: Cmnd 3095","uuid":"cd8b829f-e0e7-401e-9bdc-b6397e60bb04","lb_document_id":66459,"library":"library2_lib","document_path":"D:\\KVData\\Library2\\pdf\\1966-TS0052.pdf","level_code":0,"id":66459,"document_url":"https://treaties.fcdo.gov.uk/data/Library2\\pdf\\1966-TS0052.pdf","metaformat":"Other"},{"aw_search_query":"qs=[*],qt=[16],qr=[false],qf=[library==>library2_lib||]","thumbnail":"\\pdf\\THUMBNAIL\\1966-TS0053.png","aw_rank":1000,"product_size":"83 KB","aw_library_id":"library2_lib","title":"Treaty Series 053/1966: Cmnd 3097","uuid":"c7731018-9394-4275-af23-c8c1fb7ac8f0","lb_document_id":66460,"library":"library2_lib","document_path":"D:\\KVData\\Library2\\pdf\\1966-TS0053.pdf","level_code":0,"id":66460,"document_url":"https://treaties.fcdo.gov.uk/data/Library2\\pdf\\1966-TS0053.pdf","metaformat":"Other"},{"aw_search_query":"qs=[*],qt=[16],qr=[false],qf=[library==>library2_lib||]","thumbnail":"\\pdf\\THUMBNAIL\\1966-TS0054.png","aw_rank":1000,"product_size":"1,510 KB","aw_library_id":"library2_lib","title":"Treaty Series 054/1966: Cmnd 3110","uuid":"2c0da42a-fd06-485c-b30b-032b424c21a0","lb_document_id":66461,"library":"library2_lib","document_path":"D:\\KVData\\Library2\\pdf\\1966-TS0054.pdf","level_code":0,"id":66461,"document_url":"https://treaties.fcdo.gov.uk/data/Library2\\pdf\\1966-TS0054.pdf","metaformat":"Other"},{"aw_search_query":"qs=[*],qt=[16],qr=[false],qf=[library==>library2_lib||]","thumbnail":"\\pdf\\THUMBNAIL\\1966-TS0055.png","aw_rank":1000,"product_size":"178 KB","aw_library_id":"library2_lib","title":"Treaty Series 055/1966: Cmnd 3111","uuid":"fc59b31e-857b-4fb1-8768-73708ca4910a","lb_document_id":66462,"library":"library2_lib","document_path":"D:\\KVData\\Library2\\pdf\\1966-TS0055.pdf","level_code":0,"id":66462,"document_url":"https://treaties.fcdo.gov.uk/data/Library2\\pdf\\1966-TS0055.pdf","metaformat":"Other"},{"aw_search_query":"qs=[*],qt=[16],qr=[false],qf=[library==>library2_lib||]","thumbnail":"\\pdf\\THUMBNAIL\\1966-TS0056.png","aw_rank":1000,"product_size":"91 KB","aw_library_id":"library2_lib","title":"Treaty Series 056/1966: Cmnd 3098","uuid":"88673fd0-a46e-44ea-96f9-3b553c83df70","lb_document_id":66463,"library":"library2_lib","document_path":"D:\\KVData\\Library2\\pdf\\1966-TS0056.pdf","level_code":0,"id":66463,"document_url":"https://treaties.fcdo.gov.uk/data/Library2\\pdf\\1966-TS0056.pdf","metaformat":"Other"},{"aw_search_query":"qs=[*],qt=[16],qr=[false],qf=[library==>library2_lib||]","thumbnail":"\\pdf\\THUMBNAIL\\1966-TS0057.png","aw_rank":1000,"product_size":"116 KB","aw_library_id":"library2_lib","title":"Treaty Series 057/1966: Cmnd 3105","uuid":"8e8c44b8-9df0-4aee-8596-91fab88d7f98","lb_document_id":66464,"library":"library2_lib","document_path":"D:\\KVData\\Library2\\pdf\\1966-TS0057.pdf","level_code":0,"id":66464,"document_url":"https://treaties.fcdo.gov.uk/data/Library2\\pdf\\1966-TS0057.pdf","metaformat":"Other"},{"aw_search_query":"qs=[*],qt=[16],qr=[false],qf=[library==>library2_lib||]","thumbnail":"\\pdf\\THUMBNAIL\\1966-TS0058.png","aw_rank":1000,"product_size":"658 KB","aw_library_id":"library2_lib","title":"Treaty Series 058/1966: Cmnd 3161","uuid":"6633047e-86ce-4156-a41e-303005f73406","lb_document_id":66465,"library":"library2_lib","document_path":"D:\\KVData\\Library2\\pdf\\1966-TS0058.pdf","level_code":0,"id":66465,"document_url":"https://treaties.fcdo.gov.uk/data/Library2\\pdf\\1966-TS0058.pdf","metaformat":"Other"},{"aw_search_query":"qs=[*],qt=[16],qr=[false],qf=[library==>library2_lib||]","thumbnail":"\\pdf\\THUMBNAIL\\1966-TS0059.png","aw_rank":1000,"product_size":"169 KB","aw_library_id":"library2_lib","title":"Treaty Series 059/1966: Cmnd 3109","uuid":"0e005e45-174d-4c87-9c39-c7d3dde76fee","lb_document_id":66466,"library":"library2_lib","document_path":"D:\\KVData\\Library2\\pdf\\1966-TS0059.pdf","level_code":0,"id":66466,"document_url":"https://treaties.fcdo.gov.uk/data/Library2\\pdf\\1966-TS0059.pdf","metaformat":"Other"},{"aw_search_query":"qs=[*],qt=[16],qr=[false],qf=[library==>library2_lib||]","thumbnail":"\\pdf\\THUMBNAIL\\1966-TS0060.png","aw_rank":1000,"product_size":"269 KB","aw_library_id":"library2_lib","title":"Treaty Series 060/1966: Cmnd 3152","uuid":"c15ac613-d804-44db-ad18-6fb18e2b6a59","lb_document_id":66467,"library":"library2_lib","document_path":"D:\\KVData\\Library2\\pdf\\1966-TS0060.pdf","level_code":0,"id":66467,"document_url":"https://treaties.fcdo.gov.uk/data/Library2\\pdf\\1966-TS0060.pdf","metaformat":"Other"},{"aw_search_query":"qs=[*],qt=[16],qr=[false],qf=[library==>library2_lib||]","thumbnail":"\\pdf\\THUMBNAIL\\1966-TS0061.png","aw_rank":1000,"product_size":"688 KB","aw_library_id":"library2_lib","title":"Treaty Series 061/1966: Cmnd 3132","uuid":"9f97b50e-7fcd-411a-87c2-cc0b4285153c","lb_document_id":66468,"library":"library2_lib","document_path":"D:\\KVData\\Library2\\pdf\\1966-TS0061.pdf","level_code":0,"id":66468,"document_url":"https://treaties.fcdo.gov.uk/data/Library2\\pdf\\1966-TS0061.pdf","metaformat":"Other"},{"aw_search_query":"qs=[*],qt=[16],qr=[false],qf=[library==>library2_lib||]","thumbnail":"\\pdf\\THUMBNAIL\\1966-TS0062.png","aw_rank":1000,"product_size":"694 KB","aw_library_id":"library2_lib","title":"Treaty Series 062/1966: Cmnd 3113","uuid":"7e92ffea-996e-4b07-a423-b7a185f4fa3d","lb_document_id":66469,"library":"library2_lib","document_path":"D:\\KVData\\Library2\\pdf\\1966-TS0062.pdf","level_code":0,"id":66469,"document_url":"https://treaties.fcdo.gov.uk/data/Library2\\pdf\\1966-TS0062.pdf","metaformat":"Other"},{"aw_search_query":"qs=[*],qt=[16],qr=[false],qf=[library==>library2_lib||]","thumbnail":"\\pdf\\THUMBNAIL\\1966-TS0064.png","aw_rank":1000,"product_size":"348 KB","aw_library_id":"library2_lib","title":"Treaty Series 064/1966: Cmnd 3134","uuid":"7fb99503-86ff-403c-9893-e98da6d83ec7","lb_document_id":66470,"library":"library2_lib","document_path":"D:\\KVData\\Library2\\pdf\\1966-TS0064.pdf","level_code":0,"id":66470,"document_url":"https://treaties.fcdo.gov.uk/data/Library2\\pdf\\1966-TS0064.pdf","metaformat":"Other"},{"aw_search_query":"qs=[*],qt=[16],qr=[false],qf=[library==>library2_lib||]","thumbnail":"\\pdf\\THUMBNAIL\\1966-TS0065.png","aw_rank":1000,"product_size":"554 KB","aw_library_id":"library2_lib","title":"Treaty Series 065/1966: Cmnd 3128","uuid":"8604c04f-419c-4844-8f8b-191a9d654dae","lb_document_id":66471,"library":"library2_lib","document_path":"D:\\KVData\\Library2\\pdf\\1966-TS0065.pdf","level_code":0,"id":66471,"document_url":"https://treaties.fcdo.gov.uk/data/Library2\\pdf\\1966-TS0065.pdf","metaformat":"Other"},{"aw_search_query":"qs=[*],qt=[16],qr=[false],qf=[library==>library2_lib||]","thumbnail":"\\pdf\\THUMBNAIL\\1966-TS0066.png","aw_rank":1000,"product_size":"101 KB","aw_library_id":"library2_lib","title":"Treaty Series 066/1966: Cmnd 3133","uuid":"1fc0c0e9-6e42-404d-a442-3edfc701f37c","lb_document_id":66472,"library":"library2_lib","document_path":"D:\\KVData\\Library2\\pdf\\1966-TS0066.pdf","level_code":0,"id":66472,"document_url":"https://treaties.fcdo.gov.uk/data/Library2\\pdf\\1966-TS0066.pdf","metaformat":"Other"},{"aw_search_query":"qs=[*],qt=[16],qr=[false],qf=[library==>library2_lib||]","thumbnail":"\\pdf\\THUMBNAIL\\1966-TS0068.png","aw_rank":1000,"product_size":"194 KB","aw_library_id":"library2_lib","title":"Treaty Series 068/1966: Cmnd 3139","uuid":"928b6241-cb82-49f7-87d8-83b819cfba60","lb_document_id":66473,"library":"library2_lib","document_path":"D:\\KVData\\Library2\\pdf\\1966-TS0068.pdf","level_code":0,"id":66473,"document_url":"https://treaties.fcdo.gov.uk/data/Library2\\pdf\\1966-TS0068.pdf","metaformat":"Other"},{"aw_search_query":"qs=[*],qt=[16],qr=[false],qf=[library==>library2_lib||]","thumbnail":"\\pdf\\THUMBNAIL\\1966-TS0070.png","aw_rank":1000,"product_size":"2,382 KB","aw_library_id":"library2_lib","title":"Treaty Series 070/1966: Cmnd 3141","uuid":"b8ad5c9e-83b7-471d-b7d5-dc6025dd68fe","lb_document_id":66474,"library":"library2_lib","document_path":"D:\\KVData\\Library2\\pdf\\1966-TS0070.pdf","level_code":0,"id":66474,"document_url":"https://treaties.fcdo.gov.uk/data/Library2\\pdf\\1966-TS0070.pdf","metaformat":"Other"},{"aw_search_query":"qs=[*],qt=[16],qr=[false],qf=[library==>library2_lib||]","thumbnail":"\\pdf\\THUMBNAIL\\1966-TS0072.png","aw_rank":1000,"product_size":"1,753 KB","aw_library_id":"library2_lib","title":"Treaty Series 072/1966: Cmnd 3143","uuid":"e69202e6-f1d8-4417-8a8a-03de55a0a088","lb_document_id":66475,"library":"library2_lib","document_path":"D:\\KVData\\Library2\\pdf\\1966-TS0072.pdf","level_code":0,"id":66475,"document_url":"https://treaties.fcdo.gov.uk/data/Library2\\pdf\\1966-TS0072.pdf","metaformat":"Other"},{"aw_search_query":"qs=[*],qt=[16],qr=[false],qf=[library==>library2_lib||]","thumbnail":"\\pdf\\THUMBNAIL\\1966-TS0074.png","aw_rank":1000,"product_size":"1,149 KB","aw_library_id":"library2_lib","title":"Treaty Series 074/1966: Cmnd 3147","uuid":"222bd048-6642-4666-8a62-668c084a8a61","lb_document_id":66476,"library":"library2_lib","document_path":"D:\\KVData\\Library2\\pdf\\1966-TS0074.pdf","level_code":0,"id":66476,"document_url":"https://treaties.fcdo.gov.uk/data/Library2\\pdf\\1966-TS0074.pdf","metaformat":"Other"},{"aw_search_query":"qs=[*],qt=[16],qr=[false],qf=[library==>library2_lib||]","thumbnail":"\\pdf\\THUMBNAIL\\1966-TS0075.png","aw_rank":1000,"product_size":"300 KB","aw_library_id":"library2_lib","title":"Treaty Series 075/1966: Cmnd 3148","uuid":"24f08208-374a-47ae-8a2f-dca2442b94f9","lb_document_id":66477,"library":"library2_lib","document_path":"D:\\KVData\\Library2\\pdf\\1966-TS0075.pdf","level_code":0,"id":66477,"document_url":"https://treaties.fcdo.gov.uk/data/Library2\\pdf\\1966-TS0075.pdf","metaformat":"Other"},{"aw_search_query":"qs=[*],qt=[16],qr=[false],qf=[library==>library2_lib||]","thumbnail":"\\pdf\\THUMBNAIL\\1966-TS0078.png","aw_rank":1000,"product_size":"80 KB","aw_library_id":"library2_lib","title":"Treaty Series 078/1966: Cmnd 3156","uuid":"e5283b48-98c3-4dde-bde8-23c5412d73b5","lb_document_id":66478,"library":"library2_lib","document_path":"D:\\KVData\\Library2\\pdf\\1966-TS0078.pdf","level_code":0,"id":66478,"document_url":"https://treaties.fcdo.gov.uk/data/Library2\\pdf\\1966-TS0078.pdf","metaformat":"Other"},{"aw_search_query":"qs=[*],qt=[16],qr=[false],qf=[library==>library2_lib||]","thumbnail":"\\pdf\\THUMBNAIL\\1967-TS0001.png","aw_rank":1000,"product_size":"321 KB","aw_library_id":"library2_lib","title":"Treaty Series 001/1967: Cmnd 3168","uuid":"48b5714f-667d-4b8b-a16c-325348d1fd7d","lb_document_id":66480,"library":"library2_lib","document_path":"D:\\KVData\\Library2\\pdf\\1967-TS0001.pdf","level_code":0,"id":66480,"document_url":"https://treaties.fcdo.gov.uk/data/Library2\\pdf\\1967-TS0001.pdf","metaformat":"Other"},{"aw_search_query":"qs=[*],qt=[16],qr=[false],qf=[library==>library2_lib||]","thumbnail":"\\pdf\\THUMBNAIL\\1967-TS0002.png","aw_rank":1000,"product_size":"992 KB","aw_library_id":"library2_lib","title":"Treaty Series 002/1967: Cmnd 3166","uuid":"3b234a42-0872-4257-bc5a-3fd7d8a6490d","lb_document_id":66481,"library":"library2_lib","document_path":"D:\\KVData\\Library2\\pdf\\1967-TS0002.pdf","level_code":0,"id":66481,"document_url":"https://treaties.fcdo.gov.uk/data/Library2\\pdf\\1967-TS0002.pdf","metaformat":"Other"},{"aw_search_query":"qs=[*],qt=[16],qr=[false],qf=[library==>library2_lib||]","thumbnail":"\\pdf\\THUMBNAIL\\1967-TS0003.png","aw_rank":1000,"product_size":"388 KB","aw_library_id":"library2_lib","title":"Treaty Series 003/1967: Cmnd 3177","uuid":"f3fd1844-a808-44e6-8ce5-6d143fa07146","lb_document_id":66482,"library":"library2_lib","document_path":"D:\\KVData\\Library2\\pdf\\1967-TS0003.pdf","level_code":0,"id":66482,"document_url":"https://treaties.fcdo.gov.uk/data/Library2\\pdf\\1967-TS0003.pdf","metaformat":"Other"},{"aw_search_query":"qs=[*],qt=[16],qr=[false],qf=[library==>library2_lib||]","thumbnail":"\\pdf\\THUMBNAIL\\1967-TS0004.png","aw_rank":1000,"product_size":"132 KB","aw_library_id":"library2_lib","title":"Treaty Series 004/1967: Cmnd 3178","uuid":"2ab17150-50fd-4710-b334-3ade667b6cb7","lb_document_id":66483,"library":"library2_lib","document_path":"D:\\KVData\\Library2\\pdf\\1967-TS0004.pdf","level_code":0,"id":66483,"document_url":"https://treaties.fcdo.gov.uk/data/Library2\\pdf\\1967-TS0004.pdf","metaformat":"Other"},{"aw_search_query":"qs=[*],qt=[16],qr=[false],qf=[library==>library2_lib||]","thumbnail":"\\pdf\\THUMBNAIL\\1967-TS0006.png","aw_rank":1000,"product_size":"147 KB","aw_library_id":"library2_lib","title":"Treaty Series 006/1967: Cmd 3182","uuid":"5e9334fe-f433-44f1-af27-4975015cd0b6","lb_document_id":66484,"library":"library2_lib","document_path":"D:\\KVData\\Library2\\pdf\\1967-TS0006.pdf","level_code":0,"id":66484,"document_url":"https://treaties.fcdo.gov.uk/data/Library2\\pdf\\1967-TS0006.pdf","metaformat":"Other"},{"aw_search_query":"qs=[*],qt=[16],qr=[false],qf=[library==>library2_lib||]","thumbnail":"\\pdf\\THUMBNAIL\\1967-TS0007.png","aw_rank":1000,"product_size":"262 KB","aw_library_id":"library2_lib","title":"Treaty Series 007/1967: Cmnd 3185","uuid":"ef73f7d9-de6d-4338-aa6a-9fd6f84313ad","lb_document_id":66485,"library":"library2_lib","document_path":"D:\\KVData\\Library2\\pdf\\1967-TS0007.pdf","level_code":0,"id":66485,"document_url":"https://treaties.fcdo.gov.uk/data/Library2\\pdf\\1967-TS0007.pdf","metaformat":"Other"},{"aw_search_query":"qs=[*],qt=[16],qr=[false],qf=[library==>library2_lib||]","thumbnail":"\\pdf\\THUMBNAIL\\1967-TS0008.png","aw_rank":1000,"product_size":"635 KB","aw_library_id":"library2_lib","title":"Treaty Series 008/1967: Cmnd 3191","uuid":"28c2cda2-d94b-4236-a063-9be9d96aa5e5","lb_document_id":66486,"library":"library2_lib","document_path":"D:\\KVData\\Library2\\pdf\\1967-TS0008.pdf","level_code":0,"id":66486,"document_url":"https://treaties.fcdo.gov.uk/data/Library2\\pdf\\1967-TS0008.pdf","metaformat":"Other"},{"aw_search_query":"qs=[*],qt=[16],qr=[false],qf=[library==>library2_lib||]","thumbnail":"\\pdf\\THUMBNAIL\\1967-TS0009.png","aw_rank":1000,"product_size":"413 KB","aw_library_id":"library2_lib","title":"Treaty Series 009/1967: Cmnd 3205","uuid":"98a061f1-e0eb-45ea-8714-6abbaf9655d4","lb_document_id":66487,"library":"library2_lib","document_path":"D:\\KVData\\Library2\\pdf\\1967-TS0009.pdf","level_code":0,"id":66487,"document_url":"https://treaties.fcdo.gov.uk/data/Library2\\pdf\\1967-TS0009.pdf","metaformat":"Other"},{"aw_search_query":"qs=[*],qt=[16],qr=[false],qf=[library==>library2_lib||]","thumbnail":"\\pdf\\THUMBNAIL\\1967-TS0011.png","aw_rank":1000,"product_size":"210 KB","aw_library_id":"library2_lib","title":"Treaty Series 011/1967: Cmnd 3207","uuid":"dd574c55-68ca-4d08-8fc2-011cc83e61a8","lb_document_id":66488,"library":"library2_lib","document_path":"D:\\KVData\\Library2\\pdf\\1967-TS0011.pdf","level_code":0,"id":66488,"document_url":"https://treaties.fcdo.gov.uk/data/Library2\\pdf\\1967-TS0011.pdf","metaformat":"Other"},{"aw_search_query":"qs=[*],qt=[16],qr=[false],qf=[library==>library2_lib||]","thumbnail":"\\pdf\\THUMBNAIL\\1967-TS0012.png","aw_rank":1000,"product_size":"881 KB","aw_library_id":"library2_lib","title":"Treaty Series 012/1967: Cmnd 3212","uuid":"d3943a6f-5a90-491f-b927-3e914c76f8ec","lb_document_id":66489,"library":"library2_lib","document_path":"D:\\KVData\\Library2\\pdf\\1967-TS0012.pdf","level_code":0,"id":66489,"document_url":"https://treaties.fcdo.gov.uk/data/Library2\\pdf\\1967-TS0012.pdf","metaformat":"Other"},{"aw_search_query":"qs=[*],qt=[16],qr=[false],qf=[library==>library2_lib||]","thumbnail":"\\pdf\\THUMBNAIL\\1967-TS0013.png","aw_rank":1000,"product_size":"366 KB","aw_library_id":"library2_lib","title":"Treaty Series 013/1967: Cmnd 3221","uuid":"5808c7d7-b74b-40e2-8dfd-48124b5afd3b","lb_document_id":66490,"library":"library2_lib","document_path":"D:\\KVData\\Library2\\pdf\\1967-TS0013.pdf","level_code":0,"id":66490,"document_url":"https://treaties.fcdo.gov.uk/data/Library2\\pdf\\1967-TS0013.pdf","metaformat":"Other"},{"aw_search_query":"qs=[*],qt=[16],qr=[false],qf=[library==>library2_lib||]","thumbnail":"\\pdf\\THUMBNAIL\\1967-TS0014.png","aw_rank":1000,"product_size":"377 KB","aw_library_id":"library2_lib","title":"Treaty Series 014/1967: Cmnd 3215","uuid":"c6513503-9dc9-4ea7-b5cd-4ddd5bc184e4","lb_document_id":66491,"library":"library2_lib","document_path":"D:\\KVData\\Library2\\pdf\\1967-TS0014.pdf","level_code":0,"id":66491,"document_url":"https://treaties.fcdo.gov.uk/data/Library2\\pdf\\1967-TS0014.pdf","metaformat":"Other"},{"aw_search_query":"qs=[*],qt=[16],qr=[false],qf=[library==>library2_lib||]","thumbnail":"\\pdf\\THUMBNAIL\\1967-TS0015.png","aw_rank":1000,"product_size":"461 KB","aw_library_id":"library2_lib","title":"Treaty Series 015/1967: Cmnd 3231","uuid":"84427eb5-2961-429d-b1e9-36a6b31c770b","lb_document_id":66492,"library":"library2_lib","document_path":"D:\\KVData\\Library2\\pdf\\1967-TS0015.pdf","level_code":0,"id":66492,"document_url":"https://treaties.fcdo.gov.uk/data/Library2\\pdf\\1967-TS0015.pdf","metaformat":"Other"},{"aw_search_query":"qs=[*],qt=[16],qr=[false],qf=[library==>library2_lib||]","thumbnail":"\\pdf\\THUMBNAIL\\1967-TS0016.png","aw_rank":1000,"product_size":"707 KB","aw_library_id":"library2_lib","title":"Treaty Series 016/1967: Cmnd 3232","uuid":"7bf28788-9d98-4879-a665-04159b66c8a1","lb_document_id":66493,"library":"library2_lib","document_path":"D:\\KVData\\Library2\\pdf\\1967-TS0016.pdf","level_code":0,"id":66493,"document_url":"https://treaties.fcdo.gov.uk/data/Library2\\pdf\\1967-TS0016.pdf","metaformat":"Other"},{"aw_search_query":"qs=[*],qt=[16],qr=[false],qf=[library==>library2_lib||]","thumbnail":"\\pdf\\THUMBNAIL\\1967-TS0017.png","aw_rank":1000,"product_size":"1,637 KB","aw_library_id":"library2_lib","title":"Treaty Series 017/1967: Cmnd 3249","uuid":"358f11da-577d-4758-8ac4-38d793949400","lb_document_id":66494,"library":"library2_lib","document_path":"D:\\KVData\\Library2\\pdf\\1967-TS0017.pdf","level_code":0,"id":66494,"document_url":"https://treaties.fcdo.gov.uk/data/Library2\\pdf\\1967-TS0017.pdf","metaformat":"Other"},{"aw_search_query":"qs=[*],qt=[16],qr=[false],qf=[library==>library2_lib||]","thumbnail":"\\pdf\\THUMBNAIL\\1967-TS0018.png","aw_rank":1000,"product_size":"245 KB","aw_library_id":"library2_lib","title":"Treaty Series 018/1967: Cmnd 3239","uuid":"895401f4-b781-4b36-8c20-08187379c9f7","lb_document_id":66495,"library":"library2_lib","document_path":"D:\\KVData\\Library2\\pdf\\1967-TS0018.pdf","level_code":0,"id":66495,"document_url":"https://treaties.fcdo.gov.uk/data/Library2\\pdf\\1967-TS0018.pdf","metaformat":"Other"},{"aw_search_query":"qs=[*],qt=[16],qr=[false],qf=[library==>library2_lib||]","thumbnail":"\\pdf\\THUMBNAIL\\1967-TS0019.png","aw_rank":1000,"product_size":"498 KB","aw_library_id":"library2_lib","title":"Treaty Series 019/1967: Cmnd 3240","uuid":"5033bbf3-fb55-495e-9994-8973cd2709e3","lb_document_id":66496,"library":"library2_lib","document_path":"D:\\KVData\\Library2\\pdf\\1967-TS0019.pdf","level_code":0,"id":66496,"document_url":"https://treaties.fcdo.gov.uk/data/Library2\\pdf\\1967-TS0019.pdf","metaformat":"Other"},{"aw_search_query":"qs=[*],qt=[16],qr=[false],qf=[library==>library2_lib||]","thumbnail":"\\pdf\\THUMBNAIL\\1967-TS0020.png","aw_rank":1000,"product_size":"91 KB","aw_library_id":"library2_lib","title":"Treaty Series 020/1967: Cmnd 3237","uuid":"ea4c11b2-856f-4178-953f-347ae84bc6b1","lb_document_id":66497,"library":"library2_lib","document_path":"D:\\KVData\\Library2\\pdf\\1967-TS0020.pdf","level_code":0,"id":66497,"document_url":"https://treaties.fcdo.gov.uk/data/Library2\\pdf\\1967-TS0020.pdf","metaformat":"Other"},{"aw_search_query":"qs=[*],qt=[16],qr=[false],qf=[library==>library2_lib||]","thumbnail":"\\pdf\\THUMBNAIL\\1967-TS0022.png","aw_rank":1000,"product_size":"70 KB","aw_library_id":"library2_lib","title":"Treaty Series 022/1967: Cmnd 3251","uuid":"d7de4c71-bd93-47f5-9ee8-1bfa422630ca","lb_document_id":66498,"library":"library2_lib","document_path":"D:\\KVData\\Library2\\pdf\\1967-TS0022.pdf","level_code":0,"id":66498,"document_url":"https://treaties.fcdo.gov.uk/data/Library2\\pdf\\1967-TS0022.pdf","metaformat":"Other"},{"aw_search_query":"qs=[*],qt=[16],qr=[false],qf=[library==>library2_lib||]","thumbnail":"\\pdf\\THUMBNAIL\\1967-TS0023.png","aw_rank":1000,"product_size":"199 KB","aw_library_id":"library2_lib","title":"Treaty Series 023/1967: Cmnd 3253","uuid":"ea339865-7c73-487e-8415-1f75d7ffd5d2","lb_document_id":66499,"library":"library2_lib","document_path":"D:\\KVData\\Library2\\pdf\\1967-TS0023.pdf","level_code":0,"id":66499,"document_url":"https://treaties.fcdo.gov.uk/data/Library2\\pdf\\1967-TS0023.pdf","metaformat":"Other"},{"aw_search_query":"qs=[*],qt=[16],qr=[false],qf=[library==>library2_lib||]","thumbnail":"\\pdf\\THUMBNAIL\\1967-TS0024.png","aw_rank":1000,"product_size":"183 KB","aw_library_id":"library2_lib","title":"Treaty Series 024/1967: Cmnd 3254","uuid":"e0e27e4e-436f-4fa9-9618-ad29f9da6e4e","lb_document_id":66500,"library":"library2_lib","document_path":"D:\\KVData\\Library2\\pdf\\1967-TS0024.pdf","level_code":0,"id":66500,"document_url":"https://treaties.fcdo.gov.uk/data/Library2\\pdf\\1967-TS0024.pdf","metaformat":"Other"},{"aw_search_query":"qs=[*],qt=[16],qr=[false],qf=[library==>library2_lib||]","thumbnail":"\\pdf\\THUMBNAIL\\1967-TS0025.png","aw_rank":1000,"product_size":"2,044 KB","aw_library_id":"library2_lib","title":"Treaty Series 025/1967: Cmnd 3255","uuid":"7964a81f-616b-4923-a3fa-5ea3dc5be6f1","lb_document_id":66501,"library":"library2_lib","document_path":"D:\\KVData\\Library2\\pdf\\1967-TS0025.pdf","level_code":0,"id":66501,"document_url":"https://treaties.fcdo.gov.uk/data/Library2\\pdf\\1967-TS0025.pdf","metaformat":"Other"},{"aw_search_query":"qs=[*],qt=[16],qr=[false],qf=[library==>library2_lib||]","thumbnail":"\\pdf\\THUMBNAIL\\1967-TS0026.png","aw_rank":1000,"product_size":"138 KB","aw_library_id":"library2_lib","title":"Treaty Series 026/1967: Cmnd 3236","uuid":"8425228a-1a3d-42dd-8285-703473736725","lb_document_id":66502,"library":"library2_lib","document_path":"D:\\KVData\\Library2\\pdf\\1967-TS0026.pdf","level_code":0,"id":66502,"document_url":"https://treaties.fcdo.gov.uk/data/Library2\\pdf\\1967-TS0026.pdf","metaformat":"Other"},{"aw_search_query":"qs=[*],qt=[16],qr=[false],qf=[library==>library2_lib||]","thumbnail":"\\pdf\\THUMBNAIL\\1967-TS0027.png","aw_rank":1000,"product_size":"127 KB","aw_library_id":"library2_lib","title":"Treaty Series 027/1967: Cmnd 3252","uuid":"65d2e16f-ebbd-4c7c-a917-faeb2927aaa5","lb_document_id":66503,"library":"library2_lib","document_path":"D:\\KVData\\Library2\\pdf\\1967-TS0027.pdf","level_code":0,"id":66503,"document_url":"https://treaties.fcdo.gov.uk/data/Library2\\pdf\\1967-TS0027.pdf","metaformat":"Other"},{"aw_search_query":"qs=[*],qt=[16],qr=[false],qf=[library==>library2_lib||]","thumbnail":"\\pdf\\THUMBNAIL\\1967-TS0028.png","aw_rank":1000,"product_size":"991 KB","aw_library_id":"library2_lib","title":"Treaty Series 028/1967: Cmnd 3261","uuid":"64162bb7-cabb-4b8d-b2ea-113537b89aef","lb_document_id":66504,"library":"library2_lib","document_path":"D:\\KVData\\Library2\\pdf\\1967-TS0028.pdf","level_code":0,"id":66504,"document_url":"https://treaties.fcdo.gov.uk/data/Library2\\pdf\\1967-TS0028.pdf","metaformat":"Other"},{"aw_search_query":"qs=[*],qt=[16],qr=[false],qf=[library==>library2_lib||]","thumbnail":"\\pdf\\THUMBNAIL\\1967-TS0029.png","aw_rank":1000,"product_size":"897 KB","aw_library_id":"library2_lib","title":"Treaty Series 029/1967: Cmnd 3262","uuid":"368587cf-7016-4e39-9c6b-364629de73cc","lb_document_id":66505,"library":"library2_lib","document_path":"D:\\KVData\\Library2\\pdf\\1967-TS0029.pdf","level_code":0,"id":66505,"document_url":"https://treaties.fcdo.gov.uk/data/Library2\\pdf\\1967-TS0029.pdf","metaformat":"Other"},{"aw_search_query":"qs=[*],qt=[16],qr=[false],qf=[library==>library2_lib||]","thumbnail":"\\pdf\\THUMBNAIL\\1967-TS0030.png","aw_rank":1000,"product_size":"826 KB","aw_library_id":"library2_lib","title":"Treaty Series 030/1967: Cmnd 3263","uuid":"16db2212-d54e-4896-b461-d67e90deb414","lb_document_id":66506,"library":"library2_lib","document_path":"D:\\KVData\\Library2\\pdf\\1967-TS0030.pdf","level_code":0,"id":66506,"document_url":"https://treaties.fcdo.gov.uk/data/Library2\\pdf\\1967-TS0030.pdf","metaformat":"Other"},{"aw_search_query":"qs=[*],qt=[16],qr=[false],qf=[library==>library2_lib||]","thumbnail":"\\pdf\\THUMBNAIL\\1967-TS0031.png","aw_rank":1000,"product_size":"292 KB","aw_library_id":"library2_lib","title":"Treaty Series 031/1967: Cmnd 3247","uuid":"613bdfdb-5205-4b56-8877-5bc6b61ddf08","lb_document_id":66507,"library":"library2_lib","document_path":"D:\\KVData\\Library2\\pdf\\1967-TS0031.pdf","level_code":0,"id":66507,"document_url":"https://treaties.fcdo.gov.uk/data/Library2\\pdf\\1967-TS0031.pdf","metaformat":"Other"},{"aw_search_query":"qs=[*],qt=[16],qr=[false],qf=[library==>library2_lib||]","thumbnail":"\\pdf\\THUMBNAIL\\1967-TS0032.png","aw_rank":1000,"product_size":"1,823 KB","aw_library_id":"library2_lib","title":"Treaty Series 032/1967: Cmnd 3283","uuid":"0ba7d3e9-8b19-4405-af4d-066359c88e2b","lb_document_id":66508,"library":"library2_lib","document_path":"D:\\KVData\\Library2\\pdf\\1967-TS0032.pdf","level_code":0,"id":66508,"document_url":"https://treaties.fcdo.gov.uk/data/Library2\\pdf\\1967-TS0032.pdf","metaformat":"Other"},{"aw_search_query":"qs=[*],qt=[16],qr=[false],qf=[library==>library2_lib||]","thumbnail":"\\pdf\\THUMBNAIL\\1967-TS0033.png","aw_rank":1000,"product_size":"125 KB","aw_library_id":"library2_lib","title":"Treaty Series 033/1967: Cmnd 3276","uuid":"9e29fd91-5f9b-4648-87cd-60c9c3fac930","lb_document_id":66509,"library":"library2_lib","document_path":"D:\\KVData\\Library2\\pdf\\1967-TS0033.pdf","level_code":0,"id":66509,"document_url":"https://treaties.fcdo.gov.uk/data/Library2\\pdf\\1967-TS0033.pdf","metaformat":"Other"},{"aw_search_query":"qs=[*],qt=[16],qr=[false],qf=[library==>library2_lib||]","thumbnail":"\\pdf\\THUMBNAIL\\1967-TS0034.png","aw_rank":1000,"product_size":"158 KB","aw_library_id":"library2_lib","title":"Treaty Series 034/1967: Cmnd 3277","uuid":"4a4e0a02-649f-45a2-a3f3-3ee52b510a88","lb_document_id":66510,"library":"library2_lib","document_path":"D:\\KVData\\Library2\\pdf\\1967-TS0034.pdf","level_code":0,"id":66510,"document_url":"https://treaties.fcdo.gov.uk/data/Library2\\pdf\\1967-TS0034.pdf","metaformat":"Other"},{"aw_search_query":"qs=[*],qt=[16],qr=[false],qf=[library==>library2_lib||]","thumbnail":"\\pdf\\THUMBNAIL\\1967-TS0035.png","aw_rank":1000,"product_size":"210 KB","aw_library_id":"library2_lib","title":"Treaty Series 035/1967: Cmnd 3278","uuid":"df91f01b-634d-4097-b4a3-e870fc49e129","lb_document_id":66511,"library":"library2_lib","document_path":"D:\\KVData\\Library2\\pdf\\1967-TS0035.pdf","level_code":0,"id":66511,"document_url":"https://treaties.fcdo.gov.uk/data/Library2\\pdf\\1967-TS0035.pdf","metaformat":"Other"},{"aw_search_query":"qs=[*],qt=[16],qr=[false],qf=[library==>library2_lib||]","thumbnail":"\\pdf\\THUMBNAIL\\1967-TS0036.png","aw_rank":1000,"product_size":"412 KB","aw_library_id":"library2_lib","title":"Treaty Series 036/1967: Cmnd 3273","uuid":"624f2606-6755-4906-a782-74f249d7539c","lb_document_id":66512,"library":"library2_lib","document_path":"D:\\KVData\\Library2\\pdf\\1967-TS0036.pdf","level_code":0,"id":66512,"document_url":"https://treaties.fcdo.gov.uk/data/Library2\\pdf\\1967-TS0036.pdf","metaformat":"Other"},{"aw_search_query":"qs=[*],qt=[16],qr=[false],qf=[library==>library2_lib||]","thumbnail":"\\pdf\\THUMBNAIL\\1967-TS0037.png","aw_rank":1000,"product_size":"1,125 KB","aw_library_id":"library2_lib","title":"Treaty Series 037/1967: Cmnd 3284","uuid":"1caf8eae-193c-49b8-af3c-a7ba2ac52a6c","lb_document_id":66513,"library":"library2_lib","document_path":"D:\\KVData\\Library2\\pdf\\1967-TS0037.pdf","level_code":0,"id":66513,"document_url":"https://treaties.fcdo.gov.uk/data/Library2\\pdf\\1967-TS0037.pdf","metaformat":"Other"},{"aw_search_query":"qs=[*],qt=[16],qr=[false],qf=[library==>library2_lib||]","thumbnail":"\\pdf\\THUMBNAIL\\1967-TS0039.png","aw_rank":1000,"product_size":"910 KB","aw_library_id":"library2_lib","title":"Treaty Series 039/1967: Cmnd 3279","uuid":"92711636-b279-4fbf-832a-6291f128fe4f","lb_document_id":66514,"library":"library2_lib","document_path":"D:\\KVData\\Library2\\pdf\\1967-TS0039.pdf","level_code":0,"id":66514,"document_url":"https://treaties.fcdo.gov.uk/data/Library2\\pdf\\1967-TS0039.pdf","metaformat":"Other"},{"aw_search_query":"qs=[*],qt=[16],qr=[false],qf=[library==>library2_lib||]","thumbnail":"\\pdf\\THUMBNAIL\\1967-TS0040.png","aw_rank":1000,"product_size":"229 KB","aw_library_id":"library2_lib","title":"Treaty Series 040/1967: Cmnd 3341","uuid":"d14fd356-8d7d-4715-9442-fcc109eb8173","lb_document_id":66515,"library":"library2_lib","document_path":"D:\\KVData\\Library2\\pdf\\1967-TS0040.pdf","level_code":0,"id":66515,"document_url":"https://treaties.fcdo.gov.uk/data/Library2\\pdf\\1967-TS0040.pdf","metaformat":"Other"},{"aw_search_query":"qs=[*],qt=[16],qr=[false],qf=[library==>library2_lib||]","thumbnail":"\\pdf\\THUMBNAIL\\1967-TS0041.png","aw_rank":1000,"product_size":"9,573 KB","aw_library_id":"library2_lib","title":"Treaty Series 041/1967: Cmnd 3383","uuid":"9d87bd26-9f06-4472-ac23-a716397dc9fd","lb_document_id":66516,"library":"library2_lib","document_path":"D:\\KVData\\Library2\\pdf\\1967-TS0041.pdf","level_code":0,"id":66516,"document_url":"https://treaties.fcdo.gov.uk/data/Library2\\pdf\\1967-TS0041.pdf","metaformat":"Other"},{"aw_search_query":"qs=[*],qt=[16],qr=[false],qf=[library==>library2_lib||]","thumbnail":"\\pdf\\THUMBNAIL\\1967-TS0042.png","aw_rank":1000,"product_size":"1,239 KB","aw_library_id":"library2_lib","title":"Treaty Series 042/1967: Cmnd 3285","uuid":"5298132b-3c25-4361-9600-bcbb2bbe41ac","lb_document_id":66517,"library":"library2_lib","document_path":"D:\\KVData\\Library2\\pdf\\1967-TS0042.pdf","level_code":0,"id":66517,"document_url":"https://treaties.fcdo.gov.uk/data/Library2\\pdf\\1967-TS0042.pdf","metaformat":"Other"},{"aw_search_query":"qs=[*],qt=[16],qr=[false],qf=[library==>library2_lib||]","thumbnail":"\\pdf\\THUMBNAIL\\1967-TS0043.png","aw_rank":1000,"product_size":"260 KB","aw_library_id":"library2_lib","title":"Treaty Series 043/1967: Cmnd 3280","uuid":"7c7cc09d-8c98-4ca5-a59f-b3c94860d3ac","lb_document_id":66518,"library":"library2_lib","document_path":"D:\\KVData\\Library2\\pdf\\1967-TS0043.pdf","level_code":0,"id":66518,"document_url":"https://treaties.fcdo.gov.uk/data/Library2\\pdf\\1967-TS0043.pdf","metaformat":"Other"},{"aw_search_query":"qs=[*],qt=[16],qr=[false],qf=[library==>library2_lib||]","thumbnail":"\\pdf\\THUMBNAIL\\1967-TS0044.png","aw_rank":1000,"product_size":"392 KB","aw_library_id":"library2_lib","title":"Treaty Series 044/1967: Cmnd 3289","uuid":"9b2e83b7-1812-4bfd-ab8e-d98ace03ee2a","lb_document_id":66519,"library":"library2_lib","document_path":"D:\\KVData\\Library2\\pdf\\1967-TS0044.pdf","level_code":0,"id":66519,"document_url":"https://treaties.fcdo.gov.uk/data/Library2\\pdf\\1967-TS0044.pdf","metaformat":"Other"}],"recordSchema":"http://www.ptfs.com/aw/istore/rware/1.0","numberOfRecordsMatched":21437,"numberOfRecordsReturned":100,"nextRecord":10518},"xmlns:ogc":"http://www.opengis.net/ogc","xmlns:ows":"http://www.opengis.net/ows","xmlns:xlink":"http://www.w3.org/1999/xlink","xmlns:xsi":"http://www.w3.org/2001/XMLSchema-instance","csw:SearchStatus":{"status":"complete","timestamp":"2022-03-12T17:46:49Z"},"xmlns:dct":"http://purl.org/dc/terms/","csw:RequestId":"adcc8954-08ae-4b0e-a441-8f01eb1b205c","xmlns:dc":"http://purl.org/dc/elements/1.1/"}}
